[
    {
        "linkTemplate": "../html/characters/template.html",
        "cardImg": "../image/characters/Nightmare/Nightmare_card.png",
        "charName": "Nightmare"
    },
    {
        "linkTemplate": "../html/characters/template.html",
        "cardImg": "../image/characters/Nightmare/Nightmare_card.png",
        "charName": "Nightmare"
    },
    {
        "linkTemplate": "../html/characters/template.html",
        "cardImg": "../image/characters/Nightmare/Nightmare_card.png",
        "charName": "Nightmare"
    },
    {
        "linkTemplate": "../html/characters/template.html",
        "cardImg": "../image/characters/Nightmare/Nightmare_card.png",
        "charName": "Nightmare"
    },
    {
        "linkTemplate": "../html/characters/template.html",
        "cardImg": "../image/characters/Nightmare/Nightmare_card.png",
        "charName": "Nightmare"
    },
    {
        "linkTemplate": "../html/characters/template.html",
        "cardImg": "../image/characters/Nightmare/Nightmare_card.png",
        "charName": "Nightmare"
    }
]